Metadata-Version: 2.1
Name: lalitsc-distributions
Version: 0.1
Summary: Gaussian and Binomial distributions
Author: Lalit Shankar Chowdhury
Author-email: lalitshankarch@gmail.com
License: MIT
